README.md
setup.py
tiny/__init__.py
tiny/main.py
tiny/settings.py
tiny/storage.py
tiny/workflow.py
tiny_cli.egg-info/PKG-INFO
tiny_cli.egg-info/SOURCES.txt
tiny_cli.egg-info/dependency_links.txt
tiny_cli.egg-info/not-zip-safe
tiny_cli.egg-info/requires.txt
tiny_cli.egg-info/top_level.txt