Metadata-Version: 2.1
Name: tiny-cli
Version: 1.0.38
Summary: TinyBio genome analysis tool
Home-page: https://github.com/tinybio-cloud/tiny
Author: TinyBio LLC
Author-email: tiny-packages@tinybio.cloud
License: MIT
Requires-Python: >=3.7
